Metadata-Version: 2.1
Name: berply
Version: 0.0.1
Summary: simple kubernetes config management system
Home-page: https://github.com/uplol/berply
License: UNKNOWN
Platform: UNKNOWN
Classifier: Programming Language :: Python :: 3
Classifier: License :: OSI Approved :: MIT License
Classifier: Operating System :: OS Independent
Requires-Python: >=3.8
